[{"JIT":{"Options":{"Expressions":true,"Optimization":true,"Deforming":true,"Inlining":true},"Functions":76,"Timing":{"Generation":6.441,"Total":373.435,"Emission":122.247,"Optimization":213.866,"Inlining":30.881}},"Planning Time":1365.132,"Triggers":[],"Plan":{"Plan Width":64,"Plan Rows":1,"Partial Mode":"Finalize","Total Cost":810681.56,"Plans":[{"Parent Relationship":"Outer","Plan Width":64,"Plan Rows":1,"Single Copy":false,"Total Cost":810681.55,"Workers Launched":0,"Plans":[{"Parent Relationship":"Outer","Plan Width":64,"Plan Rows":1,"Partial Mode":"Partial","Total Cost":809681.45,"Plans":[{"Parent Relationship":"Outer","Join Type":"Inner","Plan Width":32,"Hash Cond":"(an.person_id = n.id)","Plan Rows":1,"Inner Unique":false,"Total Cost":809681.43,"Plans":[{"Parent Relationship":"Outer","Relation Name":"q7a_aka_name","Plan Width":4,"Plan Rows":397684,"Rows Removed by Filter":226651,"Total Cost":18023.52,"Parallel Aware":true,"Actual Startup Time":0.014,"Filter":"((name)::text ~~ '%a%'::text)","Workers":[],"Alias":"an","Actual Loops":1,"Node Type":"Seq Scan","Startup Cost":0.0,"Actual Total Time":67.985,"Actual Rows":674692},{"Parent Relationship":"Inner","Hash Buckets":1024,"Plan Width":44,"Peak Memory Usage":40,"Original Hash Batches":1,"Plan Rows":1,"Total Cost":790166.58,"Plans":[{"Parent Relationship":"Outer","Join Type":"Inner","Plan Width":44,"Hash Cond":"(t.id = ml.linked_movie_id)","Plan Rows":1,"Inner Unique":false,"Total Cost":790166.58,"Plans":[{"Parent Relationship":"Outer","Join Type":"Inner","Plan Width":52,"Hash Cond":"(t.id = ci.movie_id)","Plan Rows":1,"Inner Unique":false,"Total Cost":789558.68,"Plans":[{"Parent Relationship":"Outer","Relation Name":"q7a_title","Plan Width":21,"Plan Rows":200109,"Rows Removed by Filter":2188126,"Total Cost":58306.64,"Parallel Aware":true,"Actual Startup Time":0.024,"Filter":"((production_year >= 1980) AND (production_year <= 1995))","Workers":[],"Alias":"t","Actual Loops":1,"Node Type":"Seq Scan","Startup Cost":0.0,"Actual Total Time":122.853,"Actual Rows":340186},{"Parent Relationship":"Inner","Hash Buckets":4096,"Plan Width":31,"Peak Memory Usage":248,"Original Hash Batches":1,"Plan Rows":1,"Total Cost":730501.61,"Plans":[{"Parent Relationship":"Outer","Join Type":"Inner","Plan Width":31,"Hash Cond":"(ci.person_id = n.id)","Plan Rows":1,"Inner Unique":false,"Total Cost":730501.61,"Plans":[{"Parent Relationship":"Outer","Relation Name":"cast_info","Plan Width":8,"Plan Rows":21320202,"Total Cost":465889.02,"Parallel Aware":true,"Actual Startup Time":0.014,"Workers":[],"Alias":"ci","Actual Loops":1,"Node Type":"Seq Scan","Startup Cost":0.0,"Actual Total Time":1496.969,"Actual Rows":36244344},{"Parent Relationship":"Inner","Hash Buckets":1024,"Plan Width":23,"Peak Memory Usage":40,"Original Hash Batches":1,"Plan Rows":1,"Total Cost":184661.76,"Plans":[{"Parent Relationship":"Outer","Join Type":"Inner","Plan Width":23,"Hash Cond":"(n.id = pi.person_id)","Plan Rows":1,"Inner Unique":false,"Total Cost":184661.76,"Plans":[{"Parent Relationship":"Outer","Relation Name":"q7a_name","Plan Width":19,"Plan Rows":278013,"Rows Removed by Filter":3624200,"Total Cost":110771.97,"Parallel Aware":true,"Actual Startup Time":0.011,"Filter":"(((name_pcode_cf)::text >= 'A'::text) AND ((name_pcode_cf)::text <= 'F'::text) AND (((gender)::text = 'm'::text) OR (((gender)::text = 'f'::text) AND ((name)::text ~~ 'B%'::text))))","Workers":[],"Alias":"n","Actual Loops":1,"Node Type":"Seq Scan","Startup Cost":0.0,"Actual Total Time":439.09,"Actual Rows":543291},{"Parent Relationship":"Inner","Hash Buckets":1024,"Plan Width":4,"Peak Memory Usage":40,"Original Hash Batches":1,"Plan Rows":1,"Total Cost":72847.22,"Plans":[{"Parent Relationship":"Outer","Join Type":"Inner","Plan Width":4,"Hash Cond":"(pi.info_type_id = it.id)","Plan Rows":1,"Inner Unique":false,"Total Cost":72847.22,"Plans":[{"Parent Relationship":"Outer","Relation Name":"q7a_person_info","Plan Width":8,"Plan Rows":38,"Rows Removed by Filter":2963600,"Total Cost":72844.65,"Parallel Aware":true,"Actual Startup Time":1.989,"Filter":"((note)::text = 'Volker Boehm'::text)","Workers":[],"Alias":"pi","Actual Loops":1,"Node Type":"Seq Scan","Startup Cost":0.0,"Actual Total Time":161.321,"Actual Rows":64},{"Parent Relationship":"Inner","Hash Buckets":1024,"Plan Width":4,"Peak Memory Usage":9,"Original Hash Batches":1,"Plan Rows":1,"Total Cost":2.41,"Plans":[{"Parent Relationship":"Outer","Relation Name":"q7a_info_type","Plan Width":4,"Plan Rows":1,"Rows Removed by Filter":112,"Total Cost":2.41,"Parallel Aware":false,"Actual Startup Time":0.013,"Filter":"((info)::text = 'mini biography'::text)","Workers":[],"Alias":"it","Actual Loops":1,"Node Type":"Seq Scan","Startup Cost":0.0,"Actual Total Time":0.015,"Actual Rows":1}],"Parallel Aware":false,"Actual Startup Time":0.016,"Workers":[],"Actual Loops":1,"Node Type":"Hash","Hash Batches":1,"Original Hash Buckets":1024,"Startup Cost":2.41,"Actual Total Time":0.017,"Actual Rows":1}],"Parallel Aware":false,"Actual Startup Time":2.011,"Workers":[],"Actual Loops":1,"Node Type":"Hash Join","Startup Cost":2.43,"Actual Total Time":161.361,"Actual Rows":64}],"Parallel Aware":true,"Actual Startup Time":161.385,"Workers":[],"Actual Loops":1,"Node Type":"Hash","Hash Batches":1,"Original Hash Buckets":1024,"Startup Cost":72847.22,"Actual Total Time":161.387,"Actual Rows":64}],"Parallel Aware":true,"Actual Startup Time":169.405,"Workers":[],"Actual Loops":1,"Node Type":"Hash Join","Startup Cost":72847.24,"Actual Total Time":621.081,"Actual Rows":17}],"Parallel Aware":true,"Actual Startup Time":621.094,"Workers":[],"Actual Loops":1,"Node Type":"Hash","Hash Batches":1,"Original Hash Buckets":1024,"Startup Cost":184661.76,"Actual Total Time":621.099,"Actual Rows":17}],"Parallel Aware":true,"Actual Startup Time":647.411,"Workers":[],"Actual Loops":1,"Node Type":"Hash Join","Startup Cost":184661.78,"Actual Total Time":3696.983,"Actual Rows":2670}],"Parallel Aware":true,"Actual Startup Time":3697.425,"Workers":[],"Actual Loops":1,"Node Type":"Hash","Hash Batches":1,"Original Hash Buckets":1024,"Startup Cost":730501.61,"Actual Total Time":3697.431,"Actual Rows":2670}],"Parallel Aware":true,"Actual Startup Time":3697.469,"Workers":[],"Actual Loops":1,"Node Type":"Hash Join","Startup Cost":730501.62,"Actual Total Time":3839.065,"Actual Rows":390},{"Parent Relationship":"Inner","Hash Buckets":8192,"Plan Width":4,"Peak Memory Usage":247,"Original Hash Batches":1,"Plan Rows":600,"Total Cost":600.38,"Plans":[{"Parent Relationship":"Outer","Join Type":"Inner","Plan Width":4,"Hash Cond":"(ml.link_type_id = lt.id)","Plan Rows":600,"Inner Unique":false,"Total Cost":600.38,"Plans":[{"Parent Relationship":"Outer","Relation Name":"q7a_movie_link","Plan Width":8,"Plan Rows":29997,"Total Cost":462.97,"Parallel Aware":false,"Actual Startup Time":0.012,"Workers":[],"Alias":"ml","Actual Loops":1,"Node Type":"Seq Scan","Startup Cost":0.0,"Actual Total Time":1.672,"Actual Rows":29997},{"Parent Relationship":"Inner","Hash Buckets":1024,"Plan Width":4,"Peak Memory Usage":9,"Original Hash Batches":1,"Plan Rows":4,"Total Cost":18.88,"Plans":[{"Parent Relationship":"Outer","Relation Name":"q7a_link_type","Plan Width":4,"Plan Rows":4,"Rows Removed by Filter":17,"Total Cost":18.88,"Parallel Aware":false,"Actual Startup Time":367.351,"Filter":"((link)::text = 'features'::text)","Workers":[],"Alias":"lt","Actual Loops":1,"Node Type":"Seq Scan","Startup Cost":0.0,"Actual Total Time":367.353,"Actual Rows":1}],"Parallel Aware":false,"Actual Startup Time":367.355,"Workers":[],"Actual Loops":1,"Node Type":"Hash","Hash Batches":1,"Original Hash Buckets":1024,"Startup Cost":18.88,"Actual Total Time":367.356,"Actual Rows":1}],"Parallel Aware":false,"Actual Startup Time":367.39,"Workers":[],"Actual Loops":1,"Node Type":"Hash Join","Startup Cost":18.93,"Actual Total Time":370.636,"Actual Rows":5186}],"Parallel Aware":false,"Actual Startup Time":370.934,"Workers":[],"Actual Loops":1,"Node Type":"Hash","Hash Batches":1,"Original Hash Buckets":1024,"Startup Cost":600.38,"Actual Total Time":370.935,"Actual Rows":5186}],"Parallel Aware":false,"Actual Startup Time":4171.977,"Workers":[],"Actual Loops":1,"Node Type":"Hash Join","Startup Cost":731109.5,"Actual Total Time":4210.105,"Actual Rows":14}],"Parallel Aware":true,"Actual Startup Time":4210.106,"Workers":[],"Actual Loops":1,"Node Type":"Hash","Hash Batches":1,"Original Hash Buckets":1024,"Startup Cost":790166.58,"Actual Total Time":4210.114,"Actual Rows":14}],"Parallel Aware":true,"Actual Startup Time":4212.42,"Workers":[],"Actual Loops":1,"Node Type":"Hash Join","Startup Cost":790166.59,"Actual Total Time":4304.241,"Actual Rows":32}],"Parallel Aware":false,"Actual Startup Time":4304.252,"Workers":[],"Actual Loops":1,"Node Type":"Aggregate","Strategy":"Plain","Startup Cost":809681.44,"Actual Total Time":4304.261,"Actual Rows":1}],"Parallel Aware":false,"Actual Startup Time":4304.65,"Actual Loops":1,"Workers Planned":1,"Node Type":"Gather","Startup Cost":810681.44,"Actual Total Time":4304.904,"Actual Rows":1}],"Parallel Aware":false,"Actual Startup Time":4304.656,"Actual Loops":1,"Node Type":"Aggregate","Strategy":"Plain","Startup Cost":810681.55,"Actual Total Time":4304.909,"Actual Rows":1},"Execution Time":4337.757}]